emdash_core/__init__.py
emdash_core/config.py
emdash_core/server.py
emdash_core/agent/__init__.py
emdash_core/agent/agents.py
emdash_core/agent/background.py
emdash_core/agent/code_reviewer.py
emdash_core/agent/compaction.py
emdash_core/agent/context_manager.py
emdash_core/agent/events.py
emdash_core/agent/factory.py
emdash_core/agent/handlers.py
emdash_core/agent/hooks.py
emdash_core/agent/inprocess_subagent.py
emdash_core/agent/reviewer_profile.py
emdash_core/agent/rules.py
emdash_core/agent/session.py
emdash_core/agent/skills.py
emdash_core/agent/spec_schema.py
emdash_core/agent/specification.py
emdash_core/agent/subagent.py
emdash_core/agent/subagent_prompts.py
emdash_core/agent/toolkit.py
emdash_core/agent/worktree.py
emdash_core/agent/base/__init__.py
emdash_core/agent/base/base_agent.py
emdash_core/agent/base/base_subagent.py
emdash_core/agent/coding/__init__.py
emdash_core/agent/coding/main_agent.py
emdash_core/agent/coworker/__init__.py
emdash_core/agent/coworker/main_agent.py
emdash_core/agent/coworker/toolkit.py
emdash_core/agent/mcp/__init__.py
emdash_core/agent/mcp/client.py
emdash_core/agent/mcp/config.py
emdash_core/agent/mcp/manager.py
emdash_core/agent/mcp/tool_factory.py
emdash_core/agent/prompts/__init__.py
emdash_core/agent/prompts/main_agent.py
emdash_core/agent/prompts/plan_mode.py
emdash_core/agent/prompts/subagents.py
emdash_core/agent/prompts/workflow.py
emdash_core/agent/providers/__init__.py
emdash_core/agent/providers/base.py
emdash_core/agent/providers/factory.py
emdash_core/agent/providers/models.py
emdash_core/agent/providers/openai_provider.py
emdash_core/agent/research/__init__.py
emdash_core/agent/research/agent.py
emdash_core/agent/research/controller.py
emdash_core/agent/research/critic.py
emdash_core/agent/research/macros.py
emdash_core/agent/research/planner.py
emdash_core/agent/research/researcher.py
emdash_core/agent/research/state.py
emdash_core/agent/research/synthesizer.py
emdash_core/agent/runner/__init__.py
emdash_core-0.1.107.dist-info/METADATA
emdash_core-0.1.107.dist-info/WHEEL
emdash_core-0.1.107.dist-info/entry_points.txt
emdash_core-0.1.107.dist-info/RECORD
