Metadata-Version: 2.4
Name: emdash-core
Version: 0.1.107
Summary: EmDash Core - FastAPI server for code intelligence
Author: Em Dash Team
Requires-Python: >=3.10
Requires-Dist: astroid>=3.0.1
Requires-Dist: beautifulsoup4>=4.12.0
Requires-Dist: claude-agent-sdk>=0.1.19
Requires-Dist: cmake>=3.25.0
Requires-Dist: duckduckgo-search>=6.0.0
Requires-Dist: fastapi>=0.109.0
Requires-Dist: filelock>=3.13.0
Requires-Dist: gitpython>=3.1.40
Requires-Dist: httpx>=0.25.0
Requires-Dist: kuzu>=0.4.0
Requires-Dist: loguru>=0.7.2
Requires-Dist: networkx>=3.2.1
Requires-Dist: numpy>=1.26.0
Requires-Dist: openai>=1.0.0
Requires-Dist: openpyxl>=3.1.0
Requires-Dist: pydantic-settings>=2.0.0
Requires-Dist: pydantic>=2.5.0
Requires-Dist: pygithub>=2.1.1
Requires-Dist: pyobjc-framework-cocoa>=9.0; sys_platform == 'darwin'
Requires-Dist: pypng>=0.0.21
Requires-Dist: python-docx>=1.1.0
Requires-Dist: python-dotenv>=1.0.0
Requires-Dist: python-louvain>=0.16
Requires-Dist: python-pptx>=1.0.2
Requires-Dist: pyyaml>=6.0
Requires-Dist: sse-starlette>=2.0.0
Requires-Dist: tqdm>=4.66.1
Requires-Dist: uvicorn[standard]>=0.27.0
Provides-Extra: coworker
Requires-Dist: python-pptx>=0.6.21; extra == 'coworker'
Provides-Extra: dev
Requires-Dist: pytest-asyncio>=0.23.0; extra == 'dev'
Requires-Dist: pytest-cov>=4.1.0; extra == 'dev'
Requires-Dist: pytest>=7.4.3; extra == 'dev'
Provides-Extra: firebase
Requires-Dist: google-auth>=2.0.0; extra == 'firebase'
